OpenDrive/__init__.py
OpenDrive/modules/__init__.py
OpenDrive/modules/decision_making/__init__.py
OpenDrive/modules/decision_making/alerts/__init__.py
OpenDrive/modules/decision_making/alerts/camera/__init__.py
OpenDrive/modules/decision_making/alerts/camera/close_calls_objects.py
OpenDrive/modules/decision_making/alerts/camera/distance_estimator.py
OpenDrive/modules/decision_making/alerts/camera/lane_change.py
OpenDrive/modules/decision_making/data_processing/__init__.py
OpenDrive/modules/decision_making/data_processing/data_process.py
OpenDrive/modules/decision_making/pipeline_definition/__init__.py
OpenDrive/modules/decision_making/pipeline_definition/consumer.py
OpenDrive/modules/perception/__init__.py
OpenDrive/modules/perception/pipeline_definition/__init__.py
OpenDrive/modules/perception/pipeline_definition/percep_pipeline.py
OpenDrive/modules/perception/pipeline_definition/perceptions_stream_control.py
OpenDrive/modules/perception/trained_models/__init__.py
OpenDrive/modules/perception/trained_models/lane_detection/__init__.py
OpenDrive/modules/perception/trained_models/lane_detection/get_lane_detection.py
OpenDrive/modules/perception/trained_models/objects_detection/__init__.py
OpenDrive/modules/perception/trained_models/objects_detection/get_object_detection.py
OpenDrive/modules/perception/trained_models/objects_detection/yolov8n.pt
OpenDrive/modules/perception/trained_models/traffic_sign_detection/__init__.py
OpenDrive/modules/perception/trained_models/traffic_sign_detection/get_traffic_sign_detection.py
OpenDrive/modules/perception/trained_models/traffic_sign_detection/signDetection.pt
OpenDrive/modules/sensors_prep/__init__.py
OpenDrive/modules/sensors_prep/data_acquisition/__init__.py
OpenDrive/modules/sensors_prep/data_acquisition/get_cam_img.py
OpenDrive/modules/sensors_prep/data_preprocessing/__init__.py
OpenDrive/modules/sensors_prep/data_preprocessing/image_normalization.py
OpenDrive/modules/sensors_prep/pipeline_definition/__init__.py
OpenDrive-1.0.0.dist-info/LICENSE
OpenDrive-1.0.0.dist-info/METADATA
OpenDrive-1.0.0.dist-info/WHEEL
OpenDrive-1.0.0.dist-info/top_level.txt
OpenDrive-1.0.0.dist-info/RECORD
