Metadata-Version: 2.1
Name: OpenDrive
Version: 1.0.0
Summary: OpenDrive Framework allows developers to work on detection, perception, and decision-making components, facilitating the creation of custom autonomous systems.
Home-page: https://github.com/OpenDriveDevelopment/OpenDrive
Author: OpenDrive systems
Author-email: tu.email@ejemplo.com
Classifier: Programming Language :: Python
Classifier: Programming Language :: Python :: 3
Classifier: License :: OSI Approved :: Apache Software License
Requires-Python: >=3.11
License-File: LICENSE
Requires-Dist: opencv-python<5.0.0,>=4.5.0
Requires-Dist: tensorflow>=2.9.0
Requires-Dist: ultralytics>=8.0.0
Requires-Dist: quixstreams>=3.0.0
